openhtf_plugin/__init__.py
openhtf_plugin-0.0.3.dist-info/LICENSE
openhtf_plugin-0.0.3.dist-info/METADATA
openhtf_plugin-0.0.3.dist-info/WHEEL
openhtf_plugin-0.0.3.dist-info/top_level.txt
openhtf_plugin-0.0.3.dist-info/RECORD
