Metadata-Version: 2.1
Name: openhtf-plugin
Version: 0.0.3
Summary: Simple Kiwi-TCMS plugin for OpenHTF
Home-page: https://github.com/UndyingScroll
Author: Kevin Pulley
Author-email: kpulley@imaginecommunications.com
License: UNKNOWN
Platform: UNKNOWN
Classifier: Programming Language :: Python :: 3
Classifier: License :: OSI Approved :: MIT License
Classifier: Operating System :: OS Independent
Requires-Python: >=3.6
Requires-Dist: tcms-api
